aioactioncable/__init__.py
aioactioncable/client.py
aioactioncable/subscription.py
aioactioncable-0.8.1.dist-info/LICENSE
aioactioncable-0.8.1.dist-info/WHEEL
aioactioncable-0.8.1.dist-info/METADATA
aioactioncable-0.8.1.dist-info/RECORD
