Metadata-Version: 2.1
Name: aioactioncable
Version: 0.8.1
Summary: Async library for building Ruby on Rails Action Cable clients, built on top of websockets.
Author-email: Emmanuel Riou <emmanuel.riou@protonmail.com>
Requires-Python: >=3.7
Classifier: Development Status :: 4 - Beta
Classifier: Environment :: Web Environment
Classifier: License :: OSI Approved :: MIT License
Classifier: Operating System :: OS Independent
Classifier: Programming Language :: Python :: 3 :: Only
Requires-Dist: websockets
Project-URL: Home, https://github.com/dazzl-tv/aioactioncable
